MUX 2:1/MUX 2:1 design.v
// Code your design here
module MUX_2_1(input I0,I1,sel,output y);
  assign y = sel ? I1 : I0;
endmodule

MUX 2:1/MUX_2_1_testbench.sv
// Code your testbench here
// or browse Examples
module MUX_2_1_tb();
  reg I0,I1,sel;
  wire y;
  MUX_2_1 DUT(I0,I1,sel,y);
  initial begin
    I0 = 1; I1 = 0; sel = 0;
    #10;
    I0 = 0; I1 = 1; sel = 0;
    #10;
    I0 = 1; I1 = 0; sel = 1;
    #10;
    I0 = 0; I1 = 1; sel = 1;
    #10;
    I0 = 0; I1 = 0; sel = 0;
    #10;
    I0 = 0; I1 = 0; sel = 1;
    #10;
    I0 = 1; I1 = 1; sel = 0;
    #10;
    I0 = 1; I1 = 1; sel = 1;
    $finish;
  end
  initial begin
    $dumpfile("mux2to1wave.vcd");
    $dumpvars();
  end
endmodule

MUX 2:1/mux2to1wave.vcd
$date
	Sun Sep  6 09:38:37 2026
$end
$version
	Icarus Verilog
$end
$timescale
	1s
$end
$scope module MUX_2_1_tb $end
$var wire 1 ! y $end
$var reg 1 " I0 $end
$var reg 1 # I1 $end
$var reg 1 $ sel $end
$scope module DUT $end
$var wire 1 " I0 $end
$var wire 1 # I1 $end
$var wire 1 $ sel $end
$var wire 1 ! y $end
$upscope $end
$upscope $end
$enddefinitions $end
$comment Show the parameter values. $end
$dumpall
$end
#0
$dumpvars
0$
0#
1"
1!
$end
#10
0!
1#
0"
#20
1$
0#
1"
#30
1!
1#
0"
#40
0!
0$
0#
#50
1$
#60
1!
0$
1#
1"
#70
1$
