4 bit counter/counter.v
// 4 bit counter
module counter(input clk, rst, output reg [3:0] count);
  always @(posedge clk)
    begin
      if(rst)
        count = 4'b0;
      else
        count=count+1;
    end
endmodule

4 bit counter/counter testbench.sv
// Code your testbench here
// or browse Examples
module count_tb();
  reg clk;
  reg rst;
  wire [3:0] count;
  counter DUT(clk,rst,count);
  initial
    begin
      $monitor($time,"rst = %b, count = %d", rst, count);
      $dumpfile("dump.vcd");
      $dumpvars(0,count_tb);
      clk = 1'b1;
      rst = 1'b1;
      #10;
      rst = 1'b0;
      #10;
      rst = 1'b1;
      #10;
      rst = 1'b0;
      #100;
      $finish;
    end
  always #5 clk = ~clk;
  
endmodule

4 bit counter/counter dump.vcd
$date
	Sat Aug 15 11:10:48 2026
$end
$version
	Icarus Verilog
$end
$timescale
	1s
$end
$scope module count_tb $end
$var wire 4 ! count [3:0] $end
$var reg 1 " clk $end
$var reg 1 # rst $end
$scope module DUT $end
$var wire 1 " clk $end
$var wire 1 # rst $end
$var reg 4 $ count [3:0] $end
$upscope $end
$upscope $end
$enddefinitions $end
$comment Show the parameter values. $end
$dumpall
$end
#0
$dumpvars
b0 $
1#
1"
b0 !
$end
#5
0"
#10
b1 !
b1 $
1"
0#
#15
0"
#20
b0 !
b0 $
1"
1#
#25
0"
#30
b1 !
b1 $
1"
0#
#35
0"
#40
b10 !
b10 $
1"
#45
0"
#50
b11 !
b11 $
1"
#55
0"
#60
b100 !
b100 $
1"
#65
0"
#70
b101 !
b101 $
1"
#75
0"
#80
b110 !
b110 $
1"
#85
0"
#90
b111 !
b111 $
1"
#95
0"
#100
b1000 !
b1000 $
1"
#105
0"
#110
b1001 !
b1001 $
1"
#115
0"
#120
b1010 !
b1010 $
1"
#125
0"
#130
b1011 !
b1011 $
1"
