4 bit RCA/RCA.v
// 4 bit RCA
module rca_4bit(input [3:0] a,b, input cin, output [4:0] s);
  wire w1,w2,w3;
  fa_df FA1(a[0],b[0],cin,s[0],w1);
  fa_df FA2(a[1],b[1],w1,s[1],w2);
  fa_df FA3(a[2],b[2],w2,s[2],w3);
  fa_df FA4(a[3],b[3],w3,s[3],s[4]);
endmodule
module fa_df(input a,b,cin,output sum,cout);
  assign sum = a^b^cin;
  assign cout = a&b|b&cin|a&cin;
endmodule

4 bit RCA/RCA testbench.sv
// Code your testbench here
// or browse Examples
module rca_4bit_tb();
  reg [3:0] a,b;
  reg cin;
  wire[4:0]s;
  reg[4:0]check;
  rca_4bit DUT(a,b,cin,s);
  initial begin
    $dumpfile("dump.vcd");
    $dumpvars(0, rca_4bit_tb);
  end
  initial repeat(10) begin
   
    a = $random;
    b = $random;
    cin = $random;
    check = a+b+cin;
    #10;
    $display($time, " %d+%d+%d=%d(%d)", a,b,cin,s,check);
  end
endmodule

4 bit RCA/RCA dump.vcd
$date
	Mon Aug 31 12:42:00 2026
$end
$version
	Icarus Verilog
$end
$timescale
	1s
$end
$scope module rca_4bit_tb $end
$var wire 5 ! s [4:0] $end
$var reg 4 " a [3:0] $end
$var reg 4 # b [3:0] $end
$var reg 5 $ check [4:0] $end
$var reg 1 % cin $end
$scope module DUT $end
$var wire 4 & a [3:0] $end
$var wire 4 ' b [3:0] $end
$var wire 1 % cin $end
$var wire 1 ( w3 $end
$var wire 1 ) w2 $end
$var wire 1 * w1 $end
$var wire 5 + s [4:0] $end
$scope module FA1 $end
$var wire 1 , a $end
$var wire 1 - b $end
$var wire 1 % cin $end
$var wire 1 * cout $end
$var wire 1 . sum $end
$upscope $end
$scope module FA2 $end
$var wire 1 / a $end
$var wire 1 0 b $end
$var wire 1 * cin $end
$var wire 1 ) cout $end
$var wire 1 1 sum $end
$upscope $end
$scope module FA3 $end
$var wire 1 2 a $end
$var wire 1 3 b $end
$var wire 1 ) cin $end
$var wire 1 ( cout $end
$var wire 1 4 sum $end
$upscope $end
$scope module FA4 $end
$var wire 1 5 a $end
$var wire 1 6 b $end
$var wire 1 ( cin $end
$var wire 1 7 cout $end
$var wire 1 8 sum $end
$upscope $end
$upscope $end
$upscope $end
$enddefinitions $end
$comment Show the parameter values. $end
$dumpall
$end
#0
$dumpvars
08
07
06
05
14
03
12
11
00
0/
0.
1-
0,
b110 +
1*
0)
0(
b1 '
b100 &
1%
b110 $
b1 #
b100 "
b110 !
$end
#10
17
1(
04
08
1.
b10001 !
b10001 +
01
1)
13
16
1,
1/
02
b10001 $
b1101 #
b1101 '
b11 "
b11 &
#20
1(
07
04
0.
b1000 !
b1000 +
18
1)
0-
10
03
06
0/
12
b1000 $
b10 #
b10 '
b101 "
b101 &
#30
14
08
b10100 !
b10100 +
17
13
15
b10100 $
b110 #
b110 '
b1101 "
b1101 &
#40
04
0)
11
b11010 !
b11010 +
18
00
16
b11010 $
b1100 #
b1100 '
#50
04
07
0)
0*
b1011 !
b1011 +
1.
1-
06
0,
1/
05
b1011 $
0%
b101 #
b101 '
b110 "
b110 &
#60
14
1)
01
1*
b1100 !
b1100 +
0.
10
1,
0/
b1100 $
b111 #
b111 '
b101 "
b101 &
#70
0*
1.
04
01
08
b10001 !
b10001 +
17
0-
03
1/
15
b10001 $
b10 #
b10 '
b1111 "
b1111 &
#80
14
07
0)
b1101 !
b1101 +
18
0(
1-
00
13
0,
0/
02
b1101 $
b101 #
b101 '
b1000 "
b1000 &
#90
17
1(
11
18
04
1*
b11011 !
b11011 +
1.
16
1,
12
b11011 $
1%
b1101 #
b1101 '
b1101 "
b1101 &
